README.md
setup.py
geosys/__init__.py
geosys.egg-info/PKG-INFO
geosys.egg-info/SOURCES.txt
geosys.egg-info/dependency_links.txt
geosys.egg-info/top_level.txt